capanno_utils/__init__.py
capanno_utils/add_content.py
capanno_utils/change_status.py
capanno_utils/content_maps.py
capanno_utils/exceptions.py
capanno_utils/import_content.py
capanno_utils/initialize_wf_files.py
capanno_utils/make_content_maps.py
capanno_utils/make_ids.py
capanno_utils/repo_config.py
capanno_utils/status.py
capanno_utils/validate.py
capanno_utils/validate_content.py
capanno_utils/validate_inputs.py
capanno_utils/add/__init__.py
capanno_utils/add/add_scripts.py
capanno_utils/add/add_tools.py
capanno_utils/add/add_workflows.py
capanno_utils/add/custom_actions.py
capanno_utils/classes/__init__.py
capanno_utils/classes/cwl/__init__.py
capanno_utils/classes/cwl/common_workflow_language.py
capanno_utils/classes/cwl/common_workflow_language_mixins.py
capanno_utils/classes/metadata/__init__.py
capanno_utils/classes/metadata/common_functions.py
capanno_utils/classes/metadata/metadata_base.py
capanno_utils/classes/metadata/script_metadata.py
capanno_utils/classes/metadata/shared_properties.py
capanno_utils/classes/metadata/tool_metadata.py
capanno_utils/classes/metadata/workflow_metadata.py
capanno_utils/classes/schema_salad/__init__.py
capanno_utils/classes/schema_salad/schema_salad.py
capanno_utils/helpers/__init__.py
capanno_utils/helpers/dict_tools.py
capanno_utils/helpers/file_management.py
capanno_utils/helpers/get_metadata_from_biotools.py
capanno_utils/helpers/get_paths.py
capanno_utils/helpers/import_repo.py
capanno_utils/helpers/modify_yaml_files.py
capanno_utils/helpers/string_tools.py
capanno_utils/helpers/validate_cwl.py
capanno_utils/helpers/validate_wdl.py
capanno_utils/templates/__init__.py
capanno_utils/templates/tool_templates/__init__.py
capanno_utils/templates/tool_templates/nextflow_templates.py
capanno_utils/templates/tool_templates/snakemake_templates.py
capanno_utils/templates/tool_templates/wdl_templates.py
tests/__init__.py
tests/suite.py
tests/test_add_content.py
tests/test_add_tool.py
tests/test_add_tool_instance.py
capanno_utils-0.11.2.dist-info/LICENSE
capanno_utils-0.11.2.dist-info/METADATA
capanno_utils-0.11.2.dist-info/WHEEL
capanno_utils-0.11.2.dist-info/entry_points.txt
capanno_utils-0.11.2.dist-info/top_level.txt
capanno_utils-0.11.2.dist-info/RECORD
