Metadata-Version: 2.1
Name: capanno-utils
Version: 0.11.2
Summary: Tool for managing bioinformatics content repositories.
Home-page: https://github.com/truwl/capanno-utils
Author: Karl Sebby
Author-email: karl.sebby@truwl.com
License: Apache 2.0
Platform: UNKNOWN
Classifier: Development Status :: 3 - Alpha
Classifier: License :: OSI Approved :: Apache Software License
Requires-Python: >=3.6
Requires-Dist: setuptools
Requires-Dist: requests
Requires-Dist: ruamel.yaml
Requires-Dist: semantic-version
Requires-Dist: pandoc-include
Requires-Dist: cwltool
Requires-Dist: miniwdl
